__init__.py
_version.py
magneto.py
scmagneto-0.1.3.dist-info/LICENSE
scmagneto-0.1.3.dist-info/METADATA
scmagneto-0.1.3.dist-info/WHEEL
scmagneto-0.1.3.dist-info/top_level.txt
scmagneto-0.1.3.dist-info/RECORD
